__init__.py
base.py
data.py
generator.py
gkquant.py
kernel.py
kquant.py
rff.py
utils.py
kernelquantifier/__init__.py
kernelquantifier/_version.py
kernelquantifier/base.py
kernelquantifier/data.py
kernelquantifier/generator.py
kernelquantifier/gkquant.py
kernelquantifier/kernel.py
kernelquantifier/kquant.py
kernelquantifier/rff.py
kernelquantifier/utils.py
kernelquantifier-0.0.2.dist-info/LICENCE
kernelquantifier-0.0.2.dist-info/METADATA
kernelquantifier-0.0.2.dist-info/WHEEL
kernelquantifier-0.0.2.dist-info/top_level.txt
kernelquantifier-0.0.2.dist-info/RECORD
