Metadata-Version: 2.1
Name: kernelquantifier
Version: 0.0.2
Summary: Quantification using Kernel Embedding and Random Fourier Features. On GPU and CPU.
Home-page: https://gitlab.com/bastiendussapapb/kernelquantifier
Author: Bastien Dussap
Author-email: bastien.dussap@inria.fr
License: MIT
Project-URL: KernelQuantification pypi, https://gitlab.com/bastiendussapapb/kernelquantifier
Classifier: Programming Language :: Python :: 3.9
Classifier: Development Status :: 4 - Beta
Classifier: Environment :: GPU :: NVIDIA CUDA
Classifier: License :: OSI Approved :: MIT License
Classifier: Topic :: Scientific/Engineering :: Artificial Intelligence
Classifier: Topic :: Scientific/Engineering :: Mathematics
License-File: LICENCE
Requires-Dist: torch
Requires-Dist: numpy
Requires-Dist: matplotlib
Requires-Dist: cvxopt
Requires-Dist: tqdm
Requires-Dist: pykeops
